README.md
setup.py
jd/__init__.py
jd/api.py
jd/comm/__init__.py
jd/comm/comm.py
jd/order/__init__.py
jd/order/order.py
jdl_sdk.egg-info/PKG-INFO
jdl_sdk.egg-info/SOURCES.txt
jdl_sdk.egg-info/dependency_links.txt
jdl_sdk.egg-info/requires.txt
jdl_sdk.egg-info/top_level.txt
jdl_sdk.egg-info/zip-safe
tests/__init__.py
tests/test_comm.py
tests/test_order.py
tests/test_sign.py